cfgopt/__init__.py
cfgopt/main.py
cfgopt/parser.py
cfgopt-0.7.2.dist-info/METADATA
cfgopt-0.7.2.dist-info/WHEEL
cfgopt-0.7.2.dist-info/entry_points.txt
cfgopt-0.7.2.dist-info/top_level.txt
cfgopt-0.7.2.dist-info/RECORD
