Metadata-Version: 2.1
Name: cfgopt
Version: 0.7.2
Summary: You only configure your deep learning experiment once with cfgopt.
Home-page: http://github.com/tjyuyao/cfgopt
Author: Yuyao Huang
Author-email: huangyuyao@outlook.com
License: MIT
Requires-Dist: jsbeautifier
